AUTHORS
CHANGELOG.txt
DESCRIPTION
LICENSE
MANIFEST.in
setup.py
cmsplugin_link_extended/__init__.py
cmsplugin_link_extended/cms_plugins.py
cmsplugin_link_extended/models.py
cmsplugin_link_extended.egg-info/PKG-INFO
cmsplugin_link_extended.egg-info/SOURCES.txt
cmsplugin_link_extended.egg-info/dependency_links.txt
cmsplugin_link_extended.egg-info/requires.txt
cmsplugin_link_extended.egg-info/top_level.txt
cmsplugin_link_extended/migrations/0001_initial.py
cmsplugin_link_extended/migrations/0002_auto__chg_field_linkextension_link.py
cmsplugin_link_extended/migrations/0003_auto__add_linkextended.py
cmsplugin_link_extended/migrations/0004_move_links_to_new_model.py
cmsplugin_link_extended/migrations/0005_auto__del_linkextension.py
cmsplugin_link_extended/migrations/__init__.py
cmsplugin_link_extended/templates/cmsplugin_link_extended/link.html
cmsplugin_link_extended/tests/__init__.py
cmsplugin_link_extended/tests/runtests.py
cmsplugin_link_extended/tests/south_settings.py
cmsplugin_link_extended/tests/test_settings.py
cmsplugin_link_extended/tests/urls.py
cmsplugin_link_extended/tests/coverage/coverage_status.png
cmsplugin_link_extended/tests/coverage/excludes.html
cmsplugin_link_extended/tests/coverage/index.html
cmsplugin_link_extended/tests/test_app/__init__.py
cmsplugin_link_extended/tests/test_app/models.py
cmsplugin_link_extended/tests/test_app/templates/base.html
cmsplugin_link_extended/tests/test_app/templates/cms/home.html