Metadata-Version: 1.0
Name: cmsplugin-link-extended
Version: 0.2
Summary: Extends the link plugin of django-cms.
